triplex/README.md
triplex/__init__.py
triplex/dfas.py
triplex/exceptions.py
triplex/perturbations.py
triplex/triplex.py
triplex/parsers/__init__.py
triplex/parsers/clausie.py
triplex/parsers/ollie.py
triplex/parsers/openie.py
triplex/parsers/remote.py
triplex/parsers/utils.py
triplex/parsers/pyclausie/ClausIE.py
triplex/parsers/pyclausie/SubprocessBackend.py
triplex/parsers/pyclausie/Triples.py
triplex/parsers/pyclausie/__init__.py
triplex/probings/__init__.py
triplex/probings/esnli.py
triplex/scripts/extract_from_dataset.py
triplex-0.0.18.dist-info/METADATA
triplex-0.0.18.dist-info/WHEEL
triplex-0.0.18.dist-info/licenses/LICENSE
triplex-0.0.18.dist-info/RECORD
