Metadata-Version: 2.1
Name: triplex
Version: 0.0.18
Summary: Explaining models, with Triples.
Project-URL: Homepage, https://github.com/msetzu/triplex
Project-URL: Bug Tracker, https://github.com/msetzu/triplex/issues
Author-email: Mattia Setzu <mattia.setzu@unipi.it>
License-File: LICENSE
Classifier: Development Status :: 2 - Pre-Alpha
Classifier: Intended Audience :: Developers
Classifier: License :: OSI Approved :: GNU General Public License v3 or later (GPLv3+)
Classifier: Operating System :: OS Independent
Classifier: Programming Language :: Python :: 3.10
Requires-Python: <3.11,>=3.8
Requires-Dist: click==7.1.2
Requires-Dist: fire
Requires-Dist: huggingface-hub
Requires-Dist: logzero
Requires-Dist: nltk
Requires-Dist: numpy
Requires-Dist: pandas
Requires-Dist: pyarrow
Requires-Dist: pylint
Requires-Dist: scipy
Requires-Dist: smart-open==6.3.0
Requires-Dist: spacy
Requires-Dist: spacy-legacy
Requires-Dist: spacy-wordnet==0.1.0
Requires-Dist: srsly
Requires-Dist: stanford-openie
Requires-Dist: stanfordnlp
Requires-Dist: torch
Requires-Dist: tqdm
Requires-Dist: transformers
Requires-Dist: urllib3
Requires-Dist: wasabi
Requires-Dist: wcwidth
Requires-Dist: webencodings
Requires-Dist: wget
Requires-Dist: wrapt
Requires-Dist: xxhash
